streamlit_text_like/__init__.py
streamlit_text_like/example.py
streamlit_text_like/frontend/build/.DS_Store
streamlit_text_like/frontend/build/asset-manifest.json
streamlit_text_like/frontend/build/bootstrap.min.css
streamlit_text_like/frontend/build/dislike.png
streamlit_text_like/frontend/build/index.html
streamlit_text_like/frontend/build/like-button.png
streamlit_text_like/frontend/build/precache-manifest.c009b940921d7b53dccf881cd5c5eff1.js
streamlit_text_like/frontend/build/service-worker.js
streamlit_text_like/frontend/build/thumbsup.svg
streamlit_text_like/frontend/build/static/js/2.54f0ba47.chunk.js
streamlit_text_like/frontend/build/static/js/2.54f0ba47.chunk.js.LICENSE.txt
streamlit_text_like/frontend/build/static/js/2.54f0ba47.chunk.js.map
streamlit_text_like/frontend/build/static/js/main.12fe5547.chunk.js
streamlit_text_like/frontend/build/static/js/main.12fe5547.chunk.js.map
streamlit_text_like/frontend/build/static/js/runtime-main.11ec9aca.js
streamlit_text_like/frontend/build/static/js/runtime-main.11ec9aca.js.map
streamlit_text_like-0.0.2.dist-info/METADATA
streamlit_text_like-0.0.2.dist-info/WHEEL
streamlit_text_like-0.0.2.dist-info/top_level.txt
streamlit_text_like-0.0.2.dist-info/RECORD
