Metadata-Version: 2.1
Name: streamlit-text-like
Version: 0.0.2
Summary: streamlit_text_like enables to like or dislike a text input
Home-page: https://github.com/PROFESSOR-PENGUIN/streamlit-text-like
Author: Ashish Rai
Author-email: ashishraics512@gmail.com
License: UNKNOWN
Platform: UNKNOWN
Requires-Python: >=3.6
Requires-Dist: streamlit (>=0.63)
